{
  "$schema": "https://pulsemcp.github.io/air/schemas/plugin-manifest.schema.json",
  "name": "ci-workflow",
  "title": "CI Workflow",
  "version": "1.0.0",
  "skills": [
    "zimmer-run-tests"
  ],
  "mcp_servers": [],
  "hooks": [
    "git-push-ci-reminder"
  ],
  "keywords": [
    "ci",
    "workflow"
  ],
  "description": "Bundles Zimmer's test/CI skill and the git-push CI reminder hook for a tight push→CI loop. The generic wait-for-ci skill is not bundled here — it is vendored in the catalog and already default-on for the `zimmer` root."
}
